setup.cfg
setup.py
not.egg-info/PKG-INFO
not.egg-info/SOURCES.txt
not.egg-info/dependency_links.txt
not.egg-info/entry_points.txt
not.egg-info/requires.txt
not.egg-info/top_level.txt
notpy/__init__.py
notpy/client.py
notpy/cmd.py
notpy/constants.py
notpy/enml.py
notpy/oauth.py