Metadata-Version: 1.0
Name: not
Version: 2.0.1
Summary: note without the e(vernote), the quickest dirtiest cli evernote client ever
Home-page: https://loren.pizza
Author: Loren Carvalho
Author-email: me@loren.pizza
License: MIT
Platform: UNKNOWN
